myfunctions_aliiazhanybekova/__init__.py
myfunctions_aliiazhanybekova/math.py
myfunctions_aliiazhanybekova-0.0.3.dist-info/METADATA
myfunctions_aliiazhanybekova-0.0.3.dist-info/WHEEL
myfunctions_aliiazhanybekova-0.0.3.dist-info/top_level.txt
myfunctions_aliiazhanybekova-0.0.3.dist-info/RECORD
