Metadata-Version: 2.1
Name: myfunctions_aliiazhanybekova
Version: 0.0.3
Summary: A description of your package
Home-page: UNKNOWN
Author: aliia
Author-email: aliia.zhanybekova@gmail.com
License: MIT
Platform: UNKNOWN
Classifier: Programming Language :: Python :: 3
Classifier: License :: OSI Approved :: MIT License
Classifier: Operating System :: OS Independent
Requires-Python: >=3.6
